LICENSE
MANIFEST.in
README.rst
setup.cfg
setup.py
django_urlmodel.egg-info/PKG-INFO
django_urlmodel.egg-info/SOURCES.txt
django_urlmodel.egg-info/dependency_links.txt
django_urlmodel.egg-info/requires.txt
django_urlmodel.egg-info/top_level.txt
urlmodel/__init__.py
urlmodel/base.py
urlmodel/lazy.py